<launch>

    <include file="$(find-pkg-share puzzlebot_ros)/launch/micro_ros_agent.launch.py"/>

    <node pkg="rplidar_ros" exec="rplidar_node" name="rplidar_node" output="screen"
        respawn="true" respawn_delay="3.0">
        <param name="channel_type"     value="serial"/>
        <param name="serial_port"      value="/dev/ttyUSB1"/>
        <param name="serial_baudrate"  value="115200"/>
        <param name="frame_id"         value="laser_frame"/>
        <param name="inverted"         value="false"/>
        <param name="angle_compensate" value="true"/>
        <param name="scan_mode"        value="Standard"/>
    </node>

    <include file="$(find-pkg-share puzzlebot_ros)/launch/aruco_jetson.launch.py"/>

    <node pkg="tf2_ros" exec="static_transform_publisher"
          name="laser_tf_fix"
          args="0 0 0 0 0 0 laser_frame laser"/>

    <node pkg="tf2_ros" exec="static_transform_publisher"
        name="base_frame_alias"
        args="0 0 0 0 0 0 base_footprint base"/>

    <node pkg="tf2_ros" exec="static_transform_publisher"
        name="camera_tf"
        args="0.08 0 0.05 0 0 0 base_footprint camera"/>

</launch>